sqlalchemy_bind_manager/__init__.py
sqlalchemy_bind_manager/_bind_manager.py
sqlalchemy_bind_manager/_session_handler.py
sqlalchemy_bind_manager/exceptions.py
sqlalchemy_bind_manager/py.typed
sqlalchemy_bind_manager/repository.py
sqlalchemy_bind_manager/version.py
sqlalchemy_bind_manager/_repository/__init__.py
sqlalchemy_bind_manager/_repository/abstract.py
sqlalchemy_bind_manager/_repository/async_.py
sqlalchemy_bind_manager/_repository/base_repository.py
sqlalchemy_bind_manager/_repository/common.py
sqlalchemy_bind_manager/_repository/result_presenters.py
sqlalchemy_bind_manager/_repository/sync.py
sqlalchemy_bind_manager/_unit_of_work/__init__.py
sqlalchemy_bind_manager-0.14.3.dist-info/METADATA
sqlalchemy_bind_manager-0.14.3.dist-info/WHEEL
sqlalchemy_bind_manager-0.14.3.dist-info/licenses/LICENSE
sqlalchemy_bind_manager-0.14.3.dist-info/RECORD
