Metadata-Version: 2.4
Name: sqlalchemy-bind-manager
Version: 0.14.3
Summary: A manager to easily handle multiple SQLAlchemy configurations
Project-URL: Homepage, https://febus982.github.io/sqlalchemy-bind-manager
Project-URL: Repository, https://github.com/febus982/sqlalchemy-bind-manager
Author-email: Federico Busetti <729029+febus982@users.noreply.github.com>
License-Expression: MIT
License-File: LICENSE
Keywords: config,manager,sqlalchemy
Classifier: Development Status :: 4 - Beta
Classifier: Framework :: AsyncIO
Classifier: Framework :: Pydantic
Classifier: Intended Audience :: Developers
Classifier: License :: OSI Approved :: MIT License
Classifier: Natural Language :: English
Classifier: Operating System :: OS Independent
Classifier: Programming Language :: Python
Classifier: Programming Language :: Python :: 3
Classifier: Programming Language :: Python :: 3 :: Only
Classifier: Programming Language :: Python :: 3.9
Classifier: Programming Language :: Python :: 3.10
Classifier: Programming Language :: Python :: 3.11
Classifier: Programming Language :: Python :: 3.12
Classifier: Programming Language :: Python :: 3.13
Classifier: Programming Language :: Python :: 3.14
Classifier: Topic :: Database
Classifier: Topic :: Database :: Front-Ends
Classifier: Topic :: Software Development :: Libraries :: Python Modules
Classifier: Typing :: Typed
Requires-Python: <3.15,>=3.9
Requires-Dist: pydantic<3,>=2.1.1
Requires-Dist: sqlalchemy[asyncio,mypy]~=2.0.0
